pytask_list/__main__.py
pytask_list/database.py
pytask_list/model.py
pytask_list/pytask_list.py
pytask_list-0.0.21.dist-info/LICENCE
pytask_list-0.0.21.dist-info/METADATA
pytask_list-0.0.21.dist-info/WHEEL
pytask_list-0.0.21.dist-info/top_level.txt
pytask_list-0.0.21.dist-info/RECORD
