Metadata-Version: 2.1
Name: pytask_list
Version: 0.0.21
Summary: A awesome To-do List made with python in your terminal 
Author: Pablo Troli
Author-email: brawlixo123@gmail.com.br
License: MIT License
Keywords: Todo List
License-File: LICENCE
Requires-Dist: typer
Requires-Dist: rich
